drf_gitlab_webhook/__init__.py
drf_gitlab_webhook/apps.py
drf_gitlab_webhook/classviews.py
drf_gitlab_webhook/signals.py
drf_gitlab_webhook/urls.py
drf_gitlab_webhook-0.1.dist-info/LICENSE
drf_gitlab_webhook-0.1.dist-info/METADATA
drf_gitlab_webhook-0.1.dist-info/WHEEL
drf_gitlab_webhook-0.1.dist-info/top_level.txt
drf_gitlab_webhook-0.1.dist-info/RECORD
