Metadata-Version: 2.1
Name: drf-gitlab-webhook
Version: 0.1
Summary: A drf app to catch gitlab webhooks events
Home-page: https://github.com/develatio/drf-gitlab-webhook/
Author: Develatio Technologies S.L.
Author-email: contacto@develat.io
License: MIT
Platform: UNKNOWN
Requires-Dist: Django (>=2.0)
